liteconfig_py/__init__.py
liteconfig_py/config.py
liteconfig_py/py.typed
liteconfig_py/validation.py
liteconfig_py-0.2.0.dist-info/licenses/LICENSE
tests/__init__.py
tests/test_config.py
tests/test_validation.py
liteconfig_py-0.2.0.dist-info/METADATA
liteconfig_py-0.2.0.dist-info/WHEEL
liteconfig_py-0.2.0.dist-info/top_level.txt
liteconfig_py-0.2.0.dist-info/RECORD
