Metadata-Version: 2.4
Name: liteconfig_py
Version: 0.2.0
Summary: A minimal, flexible Python configuration loader with environment variable support
Home-page: https://github.com/TickTockBent/liteconfig_py
Author: TickTockBent
Author-email: TickTockBent <benttick@gmail.com>
License: MIT
Classifier: Programming Language :: Python :: 3
Classifier: Programming Language :: Python :: 3.8
Classifier: Programming Language :: Python :: 3.9
Classifier: Programming Language :: Python :: 3.10
Classifier: Programming Language :: Python :: 3.11
Classifier: Programming Language :: Python :: 3.12
Classifier: License :: OSI Approved :: MIT License
Classifier: Operating System :: OS Independent
Classifier: Typing :: Typed
Requires-Python: >=3.8
License-File: LICENSE
Provides-Extra: yaml
Requires-Dist: PyYAML; extra == "yaml"
Provides-Extra: toml
Requires-Dist: toml; extra == "toml"
Provides-Extra: validation
Requires-Dist: pydantic>=2.0; extra == "validation"
Provides-Extra: all
Requires-Dist: PyYAML; extra == "all"
Requires-Dist: toml; extra == "all"
Requires-Dist: pydantic>=2.0; extra == "all"
Provides-Extra: dev
Requires-Dist: pytest>=7.0; extra == "dev"
Requires-Dist: pytest-cov>=4.0; extra == "dev"
Requires-Dist: mypy>=1.0; extra == "dev"
Requires-Dist: flake8>=6.0; extra == "dev"
Requires-Dist: PyYAML; extra == "dev"
Requires-Dist: toml; extra == "dev"
Requires-Dist: pydantic>=2.0; extra == "dev"
Dynamic: author
Dynamic: home-page
Dynamic: license-file
Dynamic: requires-python
